preRNG/__init__.py
prerng-0.1.dist-info/DESCRIPTION.rst
prerng-0.1.dist-info/METADATA
prerng-0.1.dist-info/RECORD
prerng-0.1.dist-info/WHEEL
prerng-0.1.dist-info/metadata.json
prerng-0.1.dist-info/top_level.txt
