Metadata-Version: 2.0
Name: prerng
Version: 0.1
Summary: in-lab time-locking of study preregistration
Home-page: https://github.com/matanmazor/preRNG/tree/master/Python/prerng
Author: Mazor Bros
Author-email: matanmazor@outlook.com
License: 3 clause bsd
Platform: UNKNOWN
